DisOAuth/__init__.py
DisOAuth/__version__.py
DisOAuth/common.py
DisOAuth/url.py
DiscordOAuth_Helper-0.0.1.dist-info/METADATA
DiscordOAuth_Helper-0.0.1.dist-info/WHEEL
DiscordOAuth_Helper-0.0.1.dist-info/top_level.txt
DiscordOAuth_Helper-0.0.1.dist-info/RECORD
