Metadata-Version: 2.1
Name: DiscordOAuth-Helper
Version: 0.0.1
Summary: Helps with discord oauth2
Project-URL: Homepage, https://github.com/Arcader717/DiscordOAuth2
Project-URL: Bug Tracker, https://github.com/Arcader717/DiscordOAuth2/issues
Requires-Python: >=3.7
